[
  {
    "title": "C++和python常用函数",
    "date": "2022-04-08T12:23:24.000Z",
    "file": "c++和python常用函数.md",
    "excerpt": "c++常用函数sort(v.begin(),v.end())```c++//向量vvector<int>v;sort(v.begin(),v.end())//数组asort(a,a+n);``````c++//可以加参数cmp//比如对inter",
    "tags": [
      "刷题",
      "笔记"
    ],
    "img": "",
    "totalPages": 25
  },
  {
    "title": "Leetcode3:无重复字符的最长子串——滑动窗口",
    "date": "2022-04-08T11:59:03.000Z",
    "file": "Leetcode3_无重复字符的最长子串——滑动窗口.md",
    "excerpt": "题目https://leetcode-cn.com/problems/longest-substring-without-repeating-characters/乍一看好像做过，再一看好像不会😂题解暴力法设字符串为`s`，假如我们要找的这段没有重复字符的序列是从",
    "tags": [
      "刷题"
    ],
    "img": ""
  },
  {
    "title": "Leetcode347:前K个高频元素——优先队列、堆",
    "date": "2022-04-07T08:55:15.000Z",
    "file": "Leetcode347_前K个高频元素——优先队列、堆.md",
    "excerpt": "题目https://leetcode-cn.com/problems/top-k-frequent-elements/从这题开始学会使用堆题解堆（heap）大顶堆：父节点的值大于子节点的值。小顶堆：父节点的值小于子节点的值。性质：根节点一定是最大（最小）值",
    "tags": [
      "刷题"
    ],
    "img": ""
  },
  {
    "title": "Leetcode310:最小高度树",
    "date": "2022-04-06T07:07:06.000Z",
    "file": "Leetcode310_最小高度树.md",
    "excerpt": "题目https://leetcode-cn.com/problems/minimum-height-trees/这是一道理论性很强，代码也很有技巧性的“中等”难度题目。题解暴力法献上我的超时代码：```pythonclassSolution:def",
    "tags": [
      "刷题"
    ],
    "img": ""
  },
  {
    "title": "Leetcode2:两数相加——链表",
    "date": "2022-04-05T08:50:12.000Z",
    "file": "Leetcode2_两数相加——链表.md",
    "excerpt": "题目https://leetcode-cn.com/problems/add-two-numbers/这道题主要是debug题解我自己写的代码：```c++/Definitionforsingly-linkedlist.structListN",
    "tags": [
      "刷题"
    ],
    "img": ""
  },
  {
    "title": "Leetcode230:二叉搜索树中第K小的元素",
    "date": "2022-04-04T07:26:44.000Z",
    "file": "Leetcode230_二叉搜索树中第K小的元素.md",
    "excerpt": "题目https://leetcode-cn.com/problems/kth-smallest-element-in-a-bst/这是一道可拓展性很高的题目题解中序遍历递归法最朴素的想法就是先中序遍历得到递增序列，然后返回序列的第`k-1`个元素。可是我们只需",
    "tags": [
      "刷题"
    ],
    "img": ""
  },
  {
    "title": "Leetcode450:删除二叉搜索树中的节点",
    "date": "2022-04-02T02:20:05.000Z",
    "file": "Leetcode450_删除二叉搜索树中的节点.md",
    "excerpt": "题目https://leetcode-cn.com/problems/delete-node-in-a-bst/这道题完全可以当作一个知识点来对待。题解思路众所周知，一颗二叉搜索树的中序遍历是一个递增序列，这是二叉搜索树最基本的性质之一。某个节点`node",
    "tags": [
      "刷题"
    ],
    "img": ""
  },
  {
    "title": "Leetcode55:跳跃游戏——贪心",
    "date": "2022-04-01T08:03:13.000Z",
    "file": "Leetcode55_跳跃游戏——贪心.md",
    "excerpt": "题目https://leetcode-cn.com/problems/jump-game/题解所谓贪心算法，我个人浅薄的理解就是每一步找局部最优解，最终找到整体最优解。那么这道题可以有这样的思路：从前往后遍历`nums`的元素，实时维护最远可以到达的位置`far",
    "tags": [
      "刷题"
    ],
    "img": ""
  },
  {
    "title": "Leetcode198:打家劫舍——动态规划",
    "date": "2022-03-31T08:20:49.000Z",
    "file": "Leetcode198_打家劫舍——动态规划.md",
    "excerpt": "题目https://leetcode-cn.com/problems/house-robber/题解看官方题解吧，官方题解写的真好。感想我是从去年CSP考试中知道动态规划这个概念的，当时考前自以为弄懂了（其实根本没弄懂），现在做了两三道题了，反而觉得又不懂了。动",
    "tags": [
      "刷题"
    ],
    "img": ""
  },
  {
    "title": "Leetcode113:路径总和——dfs、回溯",
    "date": "2022-03-30T11:19:10.000Z",
    "file": "Leetcode113_路径总和II——dfs、回溯.md",
    "excerpt": "题目https://leetcode-cn.com/problems/path-sum-ii/题解dfs无回溯我们用深度优先搜索，在搜索时把当前路径记录下来为`nums`。如果满足1.`sum(nums)==targetSum`；2.该节点是叶节点；",
    "tags": [
      "刷题"
    ],
    "img": ""
  }
]